llmglot/__init__.py
llmglot/cli.py
llmglot/agents/__init__.py
llmglot/agents/base.py
llmglot/agents/claude.py
llmglot/agents/cline.py
llmglot/agents/copilot.py
llmglot/agents/cursor.py
llmglot/agents/gemini.py
llmglot/agents/windsurf.py
llmglot/sync/__init__.py
llmglot/sync/agents.py
llmglot/sync/skills.py
llmglot-0.0.0.dist-info/METADATA
llmglot-0.0.0.dist-info/WHEEL
llmglot-0.0.0.dist-info/entry_points.txt
llmglot-0.0.0.dist-info/RECORD
