Metadata-Version: 2.4
Name: llmglot
Version: 0.0.0
Summary: Sync LLM agent configuration files (AGENTS.md, skills/) across different coding assistants
Requires-Python: >=3.12
Requires-Dist: jinja2>=3.1.6
Requires-Dist: typer>=0.21.1
